gpupoor/nvidia_smi.py
gpupoor-0.0.1.dist-info/LICENSE
gpupoor-0.0.1.dist-info/METADATA
gpupoor-0.0.1.dist-info/WHEEL
gpupoor-0.0.1.dist-info/entry_points.txt
gpupoor-0.0.1.dist-info/top_level.txt
gpupoor-0.0.1.dist-info/RECORD
