Metadata-Version: 2.1
Name: gpupoor
Version: 0.0.1
Summary: A false nvidia-smi output generator
Author: osbm
License: MIT License
Project-URL: homepage, https://github.com/osbm/gpupoor
Project-URL: repository, https://github.com/osbm/gpupoor
License-File: LICENSE
